README.rst
setup.py
noipclient/__init__.py
noipclient/noipclient.py
noipclient.egg-info/PKG-INFO
noipclient.egg-info/SOURCES.txt
noipclient.egg-info/dependency_links.txt
noipclient.egg-info/entry_points.txt
noipclient.egg-info/requires.txt
noipclient.egg-info/top_level.txt