Metadata-Version: 1.0
Name: noipclient
Version: 0.0.6
Summary: noip.com Dynamic DNS update client.
Home-page: http://github.com/acordiner/noipclient
Author: Alister Cordiner
Author-email: alister@cordiner.net
License: GPL v2
Platform: UNKNOWN
Classifier: Development Status :: 4 - Beta
Classifier: Environment :: No Input/Output (Daemon)
Classifier: Intended Audience :: End Users/Desktop
Classifier: License :: OSI Approved :: GNU General Public License v2 or later (GPLv2+)
Classifier: Natural Language :: English
Classifier: Operating System :: POSIX
Classifier: Topic :: System :: Networking
